autoscript/__init__.py
autoscript/templateproj.py
autoscript/workflow_email.py
autoscirpt-1.0.4.dist-info/LICENSE
autoscirpt-1.0.4.dist-info/METADATA
autoscirpt-1.0.4.dist-info/WHEEL
autoscirpt-1.0.4.dist-info/top_level.txt
autoscirpt-1.0.4.dist-info/RECORD
