Metadata-Version: 2.1
Name: autoscirpt
Version: 1.0.4
Summary: Daily Workflow Python Automation Script
Home-page: https://github.com/bdfd
Author: BDFD
Author-email: bdfd2005@gmail.com
Project-URL: Bug Tracker, https://github.com/bdfd
Classifier: Programming Language :: Python :: 3
Classifier: License :: OSI Approved :: MIT License
Classifier: Operating System :: OS Independent
Requires-Python: >=3.6
License-File: LICENSE
